vcai_be_common/__init__.py
vcai_be_common/json_formatter.py
vcai_be_common/log_constant.py
vcai_be_common/logs_filter.py
vcai_be_common/test_log.py
vcai_be_common-1.0.0.dist-info/METADATA
vcai_be_common-1.0.0.dist-info/RECORD
vcai_be_common-1.0.0.dist-info/WHEEL
vcai_be_common-1.0.0.dist-info/top_level.txt
