Metadata-Version: 2.1
Name: vcai-be-common
Version: 1.0.0
Summary: A log system for python-hemu
Home-page: https://www.python.org/
Author: yaoerjia
Author-email: yaoerjia@cmiot.chinamobile.com
License: UNKNOWN
Platform: UNKNOWN
Requires-Python: >=3
Requires-Dist: numpy (>=1.14)
Requires-Dist: tensorflow (>=1.7)
